{
    "/js/app.js": "/js/app.js",
    "/css/app.css": "/css/app.css",
    "/0.9bec1b90c00792de7988.hot-update.js": "/0.9bec1b90c00792de7988.hot-update.js",
    "/0.99e5d40010ad2e2a450e.hot-update.js": "/0.99e5d40010ad2e2a450e.hot-update.js",
    "/0.1dc9cd147a0aad142214.hot-update.js": "/0.1dc9cd147a0aad142214.hot-update.js",
    "/0.2fa4a68f4f2ff2b29045.hot-update.js": "/0.2fa4a68f4f2ff2b29045.hot-update.js",
    "/0.cf07bedbdd8ee8af7355.hot-update.js": "/0.cf07bedbdd8ee8af7355.hot-update.js",
    "/0.216cb3c36c186672006e.hot-update.js": "/0.216cb3c36c186672006e.hot-update.js",
    "/0.0c68cde46b4742f1b52b.hot-update.js": "/0.0c68cde46b4742f1b52b.hot-update.js",
    "/0.4177554d69e31d9ded0a.hot-update.js": "/0.4177554d69e31d9ded0a.hot-update.js",
    "/0.bfada77763e1fe515be5.hot-update.js": "/0.bfada77763e1fe515be5.hot-update.js",
    "/0.a2060f5a1443d5b659b9.hot-update.js": "/0.a2060f5a1443d5b659b9.hot-update.js",
    "/0.a8e70c6cae5747cd5cf1.hot-update.js": "/0.a8e70c6cae5747cd5cf1.hot-update.js",
    "/0.834e35f3999a633d2d40.hot-update.js": "/0.834e35f3999a633d2d40.hot-update.js",
    "/0.40655f3734a33b59a820.hot-update.js": "/0.40655f3734a33b59a820.hot-update.js",
    "/0.5642b4d26fcf67239768.hot-update.js": "/0.5642b4d26fcf67239768.hot-update.js",
    "/0.3aa18b288b48bf902b93.hot-update.js": "/0.3aa18b288b48bf902b93.hot-update.js",
    "/0.9fa17aed693f622e6d7d.hot-update.js": "/0.9fa17aed693f622e6d7d.hot-update.js",
    "/0.434f42acf78471af4684.hot-update.js": "/0.434f42acf78471af4684.hot-update.js",
    "/0.11f46d7f3e8dfd707c3c.hot-update.js": "/0.11f46d7f3e8dfd707c3c.hot-update.js",
    "/0.6b73af63dd6c376a206f.hot-update.js": "/0.6b73af63dd6c376a206f.hot-update.js",
    "/0.a2e776cc6b0abd10e6ba.hot-update.js": "/0.a2e776cc6b0abd10e6ba.hot-update.js",
    "/0.c894fc4157f1f4a805c7.hot-update.js": "/0.c894fc4157f1f4a805c7.hot-update.js",
    "/0.426dd243feae28ab8bb7.hot-update.js": "/0.426dd243feae28ab8bb7.hot-update.js",
    "/0.8c4ffd3bcfdf16b1527d.hot-update.js": "/0.8c4ffd3bcfdf16b1527d.hot-update.js",
    "/0.12d31513fb83e36db445.hot-update.js": "/0.12d31513fb83e36db445.hot-update.js",
    "/0.e18ac473ac91ac01c3c4.hot-update.js": "/0.e18ac473ac91ac01c3c4.hot-update.js",
    "/0.8152c22bf946361c4821.hot-update.js": "/0.8152c22bf946361c4821.hot-update.js",
    "/0.f33f81003db1e8d9c4f2.hot-update.js": "/0.f33f81003db1e8d9c4f2.hot-update.js",
    "/0.4762b388e2af737dd3ab.hot-update.js": "/0.4762b388e2af737dd3ab.hot-update.js",
    "/0.93f46d9179d01d752af4.hot-update.js": "/0.93f46d9179d01d752af4.hot-update.js",
    "/0.b3ffd1b30103cafe134e.hot-update.js": "/0.b3ffd1b30103cafe134e.hot-update.js",
    "/0.3ee83eb58574c4c443e7.hot-update.js": "/0.3ee83eb58574c4c443e7.hot-update.js",
    "/0.8a6b1ab1d75080b8c19c.hot-update.js": "/0.8a6b1ab1d75080b8c19c.hot-update.js"
}
